jinja2utils-0.1.1.dist-info/METADATA
jinja2utils-0.1.1.dist-info/WHEEL
jinja2utils-0.1.1.dist-info/licenses/LICENSE
jinja2utils/__init__.py
jinja2utils/elapsed.py
jinja2utils/plural.py
jinja2utils/t.py
jinja2utils/uchar.py
jinja2utils-0.1.1.dist-info/RECORD
